kopipasta/__init__.py
kopipasta/cache.py
kopipasta/file.py
kopipasta/import_parser.py
kopipasta/main.py
kopipasta/ops.py
kopipasta/patcher.py
kopipasta/prompt.py
kopipasta/tree_selector.py
kopipasta-0.45.0.dist-info/LICENSE
kopipasta-0.45.0.dist-info/METADATA
kopipasta-0.45.0.dist-info/WHEEL
kopipasta-0.45.0.dist-info/entry_points.txt
kopipasta-0.45.0.dist-info/top_level.txt
kopipasta-0.45.0.dist-info/RECORD
