Metadata-Version: 2.1
Name: kopipasta
Version: 0.45.0
Summary: A CLI tool to generate prompts with project structure and file contents
Home-page: https://github.com/mkorpela/kopipasta
Author: Mikko Korpela
Author-email: mikko.korpela@gmail.com
License: MIT
Classifier: Development Status :: 3 - Alpha
Classifier: Intended Audience :: Developers
Classifier: License :: OSI Approved :: MIT License
Classifier: Operating System :: OS Independent
Classifier: Programming Language :: Python :: 3
Classifier: Programming Language :: Python :: 3.8
Classifier: Programming Language :: Python :: 3.9
Classifier: Programming Language :: Python :: 3.10
Classifier: Programming Language :: Python :: 3.11
Classifier: Programming Language :: Python :: 3.12
Requires-Python: >=3.8
License-File: LICENSE
Requires-Dist: pyperclip==1.9.0
Requires-Dist: requests==2.32.3
Requires-Dist: Pygments==2.18.0
Requires-Dist: rich==13.8.1
Requires-Dist: click==8.2.1
Requires-Dist: prompt-toolkit==3.0.52
